Workbook

Sheet Summary
A1: Ag. Nikolaos Home — Project Balance Sheet
A2: Financial ground truth. Currency: EUR. Last updated 2026-10-05. Sources: project folder, Drive payments sheet, WhatsApp 'Evia HOME', Gmail, bank confirmations.
A4: FUNDING & POSITION
A5: Total deposited into NBG | B5: ='Funding (NBG Deposits)'!B13 -> 320000 | C5: 6 transfers Sep-2025 to May-2026 (bank statement)
A6: Property acquisition (2025) | B6: ='Property Acquisition 2025'!D19 -> 171709 | C6: Contract price €145,000 + legal/notary/tax
A7: Current NBG balance | B7: 49805 | C7: Reported 2026-10-05 (see Reconciliation > Rolling Bridge for the residual check)
A9: RENOVATION
A10: Renovation paid to date | B10: ='Renovation Ledger'!E167 -> 108161.47 | C10: All methods, de-duplicated
A11: Committed (approved, unpaid) | B11: ='Renovation Ledger'!E168 -> 15945 | C11: Electrician, metalworker, insurance, etc.
A12: Acquisition + Renovation paid | B12: ='Property Acquisition 2025'!D19+'Renovation Ledger'!E167 -> 279870.47 | C12: Total cash deployed into the project to date
A14: RECONCILIATION CHECK
A15: NBG reconciliation difference | B15: =Reconciliation!C16 -> 0 | C15: Account ties to the official statement (zero)
A17: ⚑ Open items needing your confirmation are on the 'Flags & Dedup' tab.

Sheet Renovation Ledger
A1: Renovation Ledger — Ag. Nikolaos Home
A2: Every renovation expense (Jan–Jun 2026), de-duplicated. The €380 demolition hammer drill (18-Jun) is a SEPARATE payment, paid by Vicky's card, to be deducted from the Antonis contract.
A4: Report Date | B4: Category | C4: Description | D4: Vendor / Payee | E4: Amount (€) | F4: Method | G4: From NBG? | H4: Status | I4: Payment Date
A5: 2026-01-17 | B5: Waste/Bins | C5: Recycle/waste bins (8) | D5: Kairis | E5: 992 | F5: cash | G5: Yes | H5: Paid | I5: 2026-01-17
A6: 2026-01-17 | B6: Labour | C6: Team leader/manager (11 days) | D6: Meli | E6: 880 | F6: cash | G6: Yes | H6: Paid | I6: 2026-01-17
A7: 2026-01-17 | B7: Labour | C7: Workers (18 worker-days) | D7: Workers | E7: 900 | F7: cash | G7: Yes | H7: Paid | I7: 2026-01-17
A8: 2026-01-17 | B8: Electrical | C8: Electricity materials | D8: Supplier | E8: 250 | F8: cash | G8: Yes | H8: Paid | I8: 2026-01-17
A9: 2026-01-17 | B9: Equipment | C9: Tool damage replacement | D9: - | E9: 250 | F9: cash | G9: Yes | H9: Paid | I9: 2026-01-17
A10: 2026-01-24 | B10: Waste/Bins | C10: Recycle/waste bins (2) | D10: Kairis | E10: 248 | F10: cash | G10: Yes | H10: Paid | I10: 2026-01-24
A11: 2026-01-24 | B11: Materials | C11: Cement - large storage base | D11: Amanatidis | E11: 431.48 | F11: NBG card | G11: Yes | H11: Paid | I11: 2026-01-24
A12: 2026-01-24 | B12: Labour | C12: Workers (16 worker-days) | D12: Workers | E12: 800 | F12: cash | G12: Yes | H12: Paid | I12: 2026-01-24
A13: 2026-01-24 | B13: Labour | C13: Team leader (7 days) | D13: Meli | E13: 560 | F13: cash | G13: Yes | H13: Paid | I13: 2026-01-24
A14: 2026-01-24 | B14: Equipment | C14: Tool spare parts/materials | D14: Poutichidis | E14: 120 | F14: cash | G14: Yes | H14: Paid | I14: 2026-01-24
A15: 2026-01-24 | B15: Materials | C15: Steel - large storage base | D15: Kairis | E15: 350 | F15: cash | G15: Yes | H15: Paid | I15: 2026-01-24
A16: 2026-02-02 | B16: Materials | C16: Steel reinforcements | D16: Kairis | E16: 220 | F16: cash | G16: Yes | H16: Paid | I16: 2026-02-02
... A146: 2026-06-28 | B146: Labour | C146: Workers week Jun25-28 (Yael unit + site) | D146: Workers | E146: 2600 | F146: cash | G146: Yes | H146: Paid | I146: 2026-06-29
A147: 2026-05-23 | B147: Electrical | C147: Electrician - 2 apts+2 storages+outdoor | D147: Electrician | E147: 9500 | F147: cash | G147: Yes | H147: Committed
A148: 2026-05-23 | B148: Electrical | C148: Electrical plans - submitted to authority | D148: Electrician | E148: 1000 | F148: - | G148: Yes | H148: Committed
A149: 2026-05-23 | B149: Electrical | C149: Three-phase meter (Kobi's name) | D149: Electrician | E149: 750 | F149: - | G149: Yes | H149: Committed
A150: 2026-05-23 | B150: Electrical | C150: Electrician advance - 130m piping reimb. | D150: Electrician | E150: 1000 | F150: cash | G150: Yes | H150: Committed
A151: 2026-05-23 | B151: Windows/Iron | C151: Metalworker - small storage door+window | D151: Metalworker | E151: 550 | F151: cash | G151: Yes | H151: Committed
A152: 2026-06-15 | B152: Site Works | C152: Excavator - road compaction (60t roller) | D152: Excavator | E152: 600 | F152: cash | G152: Yes | H152: Committed
A153: 2026-07-20 | B153: Legal/Admin | C153: Worker insurance Apr-Jun - partial payment | D153: EFKA | E153: 1865 | F153: cash | G153: Yes | H153: Paid | I153: 2026-07-20
A154: 2026-07-21 | B154: Legal/Admin | C154: Worker insurance Apr-Jun - second partial payment | D154: EFKA | E154: 1990 | F154: cash | G154: Yes | H154: Paid | I154: 2026-07-21
A155: 2026-06-25 | B155: Legal/Admin | C155: Worker insurance Apr-Jun - remaining balance | D155: EFKA | E155: 3 | F155: - | G155: Yes | H155: Committed
A156: 2026-07-19 | B156: Materials | C156: Kairis - partial payment (ATM shortfall from last week) | D156: Kairis | E156: 150 | F156: cash | G156: Yes | H156: Paid | I156: 2026-07-20
A157: 2026-06-24 | B157: Materials | C157: Kairis - remaining balance | D157: Kairis | E157: 45 | F157: cash | G157: Yes | H157: Committed
A158: 2026-07-11 | B158: Materials | C158: Kairis - SikaGrout HP340 order (200 bags) + steel - partly delivered Sep; outstanding balance per Vicky Oct 3 EUR1,950 incl. EUR45 old balance (Sep 29 EUR4,400 -> EUR3,000 before Oct 3 payment; EUR400 gap vs logged payments, see flag 13) | D158: Kairis | E158: 1905 | F158: cash | G158: Yes | H158: Committed
A159: 2026-07-21 | B159: Materials | C159: Kairis - partial payment toward column/beam debt | D159: Kairis | E159: 1000 | F159: cash | G159: Yes | H159: Paid | I159: 2026-07-21
A160: 2026-09-12 | B160: Plumbing | C160: Water connection fee (mains) + water meter purchase - one-off, now connected to mains supply | D160: Accountant (POS transfer attempted Sep 12, declined - payment method to be resolved) | E160: 400 | F160: pending | G160: No | H160: Committed
A161: 2026-09-29 | B161: Labour | C161: Workers wages - week of Sep 21-27 (crew back on site Sep 24) | D161: Site crew | E161: 950 | F161: cash | G161: Yes | H161: Paid | I161: 2026-09-29
A162: 2026-09-29 | B162: Materials | C162: Reinforcement steel, column ties, 15x D16 6m connecting bars + nails | D162: Supplier | E162: 750 | F162: cash | G162: Yes | H162: Paid | I162: 2026-09-29
A163: 2026-09-29 | B163: Fuel | C163: Petrol for concrete mixer (column pour) | D163: Site | E163: 40 | F163: cash | G163: Yes | H163: Paid | I163: 2026-09-29
A164: 2026-09-26 | B164: Electrical | C164: Electricity provider - 50% advance to reactivate 1969 meter + relocate to lower entrance (incl. install permit + supply approval); Vicky paid Sep 26, covered by Sep 29 withdrawal | D164: Electricity provider | E164: 250 | F164: cash | G164: Yes | H164: Paid | I164: 2026-09-29
A165: 2026-09-26 | B165: Electrical | C165: Electricity provider - remaining 50% for meter reactivation/relocation (Vicky Oct 3: paying Oct 4 from Oct 3 withdrawal) | D165: Electricity provider | E165: 250 | F165: cash | G165: Yes | H165: Paid | I165: 2026-10-04
A166: 2026-09-23 | B166: Electrical | C166: Electricity bill (meter still in Anagnostou name) - Vicky to hand cash to Stathis Oct 2 | D166: Anagnostou (Stathis) | E166: 192 | F166: cash | G166: Yes | H166: Committed
D167: PAID — total | E167: =SUMIF(H5:H166,"Paid",E5:E166) -> 108161.47
D168: COMMITTED (approved, unpaid) | E168: =SUMIF(H5:H166,"Committed",E5:E166) -> 15945
D169: PAID — from NBG (cash/transfer) | E169: =SUMIFS(E5:E166,H5:H166,"Paid",G5:G166,"Yes") -> 106133.92
D170: PAID — outside NBG (Wise/card) | E170: =SUMIFS(E5:E166,H5:H166,"Paid",G5:G166,"No") -> 2027.55

Sheet Funding (NBG Deposits)
A1: Funding — Deposits into NBG Account
A2: Israel → NBG GR18 0110 3180 0000 3180 0400 611. All amounts EUR received. Source: bank transfer confirmations in /Money Transfers.
A4: Value date | B4: Amount (€) | C4: Bank ref | D4: Greek-side confirmation | E4: Counted?
A5: 2025-09-28 | B5: 25000 | C5: 55423 | D5: PDF OtherBankMatachTransfer_25_09 to GR18-0400611 | E5: Yes
A6: 2025-09-28 | B6: 15000 | C6: 55758 | D6: PDF OtherBankMatachTransfer_26_09 | E6: Yes
A7: 2025-10-12 | B7: 130000 | C7: 63360 | D7: PDF OtherBankMatachTransfer_12_10 | E7: Yes
A8: 2026-01-11 | B8: 10000 | C8: 14452 | D8: PDF OtherBankMatachTransfer_10_01 | E8: Yes
A9: 2026-02-08 | B9: 20000 | C9: 30860 | D9: Confirmed - bank statement (ref 30860) + project_data.js | E9: Yes
A10: 2026-04-26 | B10: 70000 | C10: 70724 | D10: PDF OtherBankMatachTransfer_26_04 | E10: Yes
A11: 2026-05-31 | B11: 2000 | C11: 90833 | D11: Transfer to WISE as backup - not spent; NOT a Greek NBG deposit | E11: No
A12: 2026-07-13 | B12: 50000 | C12: wire-Jul13 | D12: Kobi confirmed - Israel to NBG transfer (Mizrahi) | E12: Yes
A13: TOTAL DEPOSITS (counted) | B13: =SUMIF(E5:E12,"Yes",B5:B12) -> 320000
A15: Ground truth: Mizrahi-Tefahot euro account statement (Sikum Haavarot Matach 2.pdf, 01/01/2024-22/06/2026). Rows above are the transfer-to-another-bank lines to the Greek NBG account in the project period. 2024 transfers (EUR 10k, 1.7k) excluded as pre-project.
A16: Israeli euro account still held ~EUR 64,786 liquid + EUR 70,000 in a term deposit (23-Apr) as of 10-Jun-2026 - available for future project funding.

Sheet Property Acquisition 2025
A1: Property Acquisition (2025)
A2: Purchase of two-storey residence + plot, Agios Nikolaos. Contract price €145,000 (objective value €239,793.82). Paid from NBG account.
A4: Date | B4: Item | C4: Payee | D4: Amount (€) | E4: From NBG? | F4: Note
A5: 2025-09-29 | B5: House payment 1 - pre-agreement advance | C5: Anagnostou | D5: 18500 | E5: Yes | F5: Bank transfer
A6: 2025-10-22 | B6: House payment 2 - via Zoe (issued check to seller) | C6: Anagnostou / Zoe | D6: 107000 | E6: Yes | F6: Bank transfer to Zoe -> check to Anagnostou
A7: 2025-10-22 | B7: House payment 2 - balance (direct) | C7: Anagnostou | D7: 19731 | E7: Yes | F7: Direct bank transfer
A8: 2025-10-17 | B8: Purchase tax (FMA, incl 0.9% joint discount) | C8: via Zoi Koliou | D8: 7410 | E8: Yes | F8: Transfer to Zoe
A9: 2025-11-05 | B9: Zoe commission | C9: Zoi Koliou | D9: 4350 | E9: Yes | F9: ATM cash via our debit card (800+2000+1000+550)
A10: 2025-11-05 | B10: Attorney - Vasiliki | C10: Vasiliki | D10: 2000 | E10: Yes | F10: Cash withdrawn by Zoe
A11: 2025-11-05 | B11: Land registration fee | C11: Vasiliki | D11: 1328 | E11: Yes | F11: Transfer to Vasiliki (pays on our behalf)
A12: 2025-10-24 | B12: Notary (Vasiliki) | C12: Mavri / Vasiliki | D12: 2490 | E12: Yes | F12: Direct bank transfer
A13: 2025-09-29 | B13: Legalization (engineer) - transfer 1 | C13: Vicky (Revolut LT) | D13: 800 | E13: Yes | F13: Pergola/rooftop/2 warehouses/wells
A14: 2025-10-01 | B14: Legalization (engineer) - transfer 2 | C14: Vicky (Revolut LT) | D14: 520 | E14: Yes
A15: 2025-10-01 | B15: Legalization (engineer) - transfer 3 | C15: Antonis | D15: 680 | E15: Yes
A16: 2025 | B16: Legalization (engineer) - cash balance | C16: Cash | D16: 3000 | E16: Yes | F16: Cash portion (total legalization = EUR 5,000)
A17: 2025 | B17: Notary & apostille - NBG account setup | C17: - | D17: 2700 | E17: No | F17: Paid from Israel (to open the account)
A18: 2025 | B18: Flight to Evia - purchase trip | C18: - | D18: 1200 | E18: No | F18: Travel, paid from Israel
C19: ACQUISITION TOTAL (all) | D19: =SUM(D5:D18) -> 171709
C20: of which paid from NBG | D20: =SUMIF(E5:E18,"Yes",D5:D18) -> 167809
A22: Source: 'Agio Nikolaos house payments' sheet, 'Actual' table. House price EUR 145,231 (18,500 + 107,000 + 19,731).

Sheet Out-of-NBG & Reimburse
A1: Payments Outside NBG + Vicky Reimbursements
A2: Project costs paid via Wise or by card (not from the NBG account), plus reimbursement transfers to Vicky. These expenses are already counted once in the Renovation Ledger.
A4: Date | B4: Item | C4: Method | D4: Amount (€) | E4: Note
A5: 2026-06-06 | B5: Bathroom fixtures (Diamantopoulos) | C5: Wise | D5: 614 | E5: In ledger
A6: 2026-06-18 | B6: Athens shopping - Yael unit fit-out | C6: card (Vicky) | D6: 972.55 | E6: In ledger; reimbursed €972.55 below
A7: 2026-06-19 | B7: Spanish tiles (Tsintonis) | C7: Wise | D7: 286 | E7: In ledger; NBG was blocked
A8: 2026-06-22 | B8: Bedding/pillows/bedspread - Yael | C8: card (Vicky) | D8: 155 | E8: In ledger; to net vs window cost
C9: Subtotal | D9: =SUM(D5:D8) -> 2027.55
A11: REIMBURSEMENTS TO VICKY (cash-flow only — not additional project cost)
A12: Date | B12: Item | C12: Method | D12: Amount (€) | E12: Note
A13: 2026-06-22 | B13: Reimburse Athens/Praktiker card spend | C13: Wise → Revolut | D13: 972.55 | E13: Settles only the €972.55 Praktiker spend (not the €380 drill). LT853250002013391261

Sheet Category Rollup
A1: Category Rollup — Paid vs Budget
A2: Paid = actuals from the Renovation Ledger (SUMIF). Budget = working estimates (Budget Overview / project_data forecast). Remaining is indicative.
A4: Category | B4: Paid to date (€) | C4: Working budget (€) | D4: Notes
A5: Labour | B5: =SUMIFS('Renovation Ledger'!E5:E166,'Renovation Ledger'!B5:B166,A5,'Renovation Ledger'!H5:H166,"Paid") -> 32650 | C5: 25000 | D5: Workers, Meli, ESAT, Ilir, contractors
A6: Materials | B6: =SUMIFS('Renovation Ledger'!E5:E166,'Renovation Ledger'!B5:B166,A6,'Renovation Ledger'!H5:H166,"Paid") -> 42357.87 | C6: 25000 | D6: Kairis main account, Amanatidis, sundries
A7: Plumbing | B7: =SUMIFS('Renovation Ledger'!E5:E166,'Renovation Ledger'!B5:B166,A7,'Renovation Ledger'!H5:H166,"Paid") -> 7119 | C7: 9000 | D7: All floors; ~€7.2k balance after water connection
A8: Electrical | B8: =SUMIFS('Renovation Ledger'!E5:E166,'Renovation Ledger'!B5:B166,A8,'Renovation Ledger'!H5:H166,"Paid") -> 2825 | C8: 11250 | D8: GF+storage approved €11,250; upper floors TBD
A9: Site Works | B9: =SUMIFS('Renovation Ledger'!E5:E166,'Renovation Ledger'!B5:B166,A9,'Renovation Ledger'!H5:H166,"Paid") -> 4300 | C9: 6000 | D9: Excavation, 160m road, compaction
A10: Roof | B10: =SUMIFS('Renovation Ledger'!E5:E166,'Renovation Ledger'!B5:B166,A10,'Renovation Ledger'!H5:H166,"Paid") -> 4225 | C10: 4500 | D10: 3F panels, storage roofs
A11: Windows/Iron | B11: =SUMIFS('Renovation Ledger'!E5:E166,'Renovation Ledger'!B5:B166,A11,'Renovation Ledger'!H5:H166,"Paid") -> 1550 | C11: 18700 | D11: Storage done; ~25 house openings upcoming
A12: Waste/Bins | B12: =SUMIFS('Renovation Ledger'!E5:E166,'Renovation Ledger'!B5:B166,A12,'Renovation Ledger'!H5:H166,"Paid") -> 2097 | C12: 2000 | D12: Recycle/waste containers
A13: Tiles | B13: =SUMIFS('Renovation Ledger'!E5:E166,'Renovation Ledger'!B5:B166,A13,'Renovation Ledger'!H5:H166,"Paid") -> 286 | C13: 25500 | D13: €286 paid; ~€25k order+install upcoming
A14: Furniture | B14: =SUMIFS('Renovation Ledger'!E5:E166,'Renovation Ledger'!B5:B166,A14,'Renovation Ledger'!H5:H166,"Paid") -> 905 | C14: 1000 | D14: Yael unit bed, mattress, bedding
A15: Legal/Admin | B15: =SUMIFS('Renovation Ledger'!E5:E166,'Renovation Ledger'!B5:B166,A15,'Renovation Ledger'!H5:H166,"Paid") -> 7666 | C15: 11350 | D15: Insurance, certificates, SIM, accountant
A16: Landscaping | B16: =SUMIFS('Renovation Ledger'!E5:E166,'Renovation Ledger'!B5:B166,A16,'Renovation Ledger'!H5:H166,"Paid") -> 300 | C16: 5000 | D16: Gardener, irrigation
A17: Fuel | B17: =SUMIFS('Renovation Ledger'!E5:E166,'Renovation Ledger'!B5:B166,A17,'Renovation Ledger'!H5:H166,"Paid") -> 360 | C17: 500 | D17: Site fuel
A18: Equipment | B18: =SUMIFS('Renovation Ledger'!E5:E166,'Renovation Ledger'!B5:B166,A18,'Renovation Ledger'!H5:H166,"Paid") -> 770.6 | C18: 500 | D18: Tools
A19: Other | B19: =SUMIFS('Renovation Ledger'!E5:E166,'Renovation Ledger'!B5:B166,A19,'Renovation Ledger'!H5:H166,"Paid") -> 750 | C19: 300 | D19: Misc
A20: TOTAL | B20: =SUM(B5:B19) -> 108161.47 | C20: =SUM(C5:C19) -> 145600

Sheet Reconciliation
A1: NBG Account Reconciliation (official statement)
A2: Account 31800400611, period 01/10/2025-25/06/2026. Ties to the cent. Source: NBG statement export25-06-2026.xlsx.
B5: Opening balance 01/10/2025 | C5: 21066.81 | D5: Embeds Sep-2025: +EUR25k +EUR15k transfers, -EUR18,500 down-payment, -fees
B6: + Deposits received (in period) | C6: 230000 | D6: EUR130k (13-Oct) + EUR10k (12-Jan) + EUR20k (09-Feb) + EUR70k (27-Apr)
B7: - Property acquisition & legal (transfers) | C7: -139459.28 | D7: House 126,730.81 + tax 7,410 + notary 2,490 + land reg 1,328.47 + owner cert 200 + land-reg temp 100 + legalization 620 + 580
B8: - Acquisition paid in cash (Nov-2025) | C8: -6350 | D8: Zoe commission 4,350 + Vasiliki 2,000
B9: - Renovation/project cash withdrawals (ATM) | C9: -64730 | D9: Cash for workers, Kairis, materials, etc.
B10: - Renovation card payments (POS) | C10: -4494.92 | D10: Amanatidis 1,524.32 + GKIZA 1,440 + aluminium 1,150 + drill 380.60
B11: - Accountant - tax registration | C11: -711 | D11: SIANOS PANTAZIS, 18-May
B12: - Personal card spend | C12: -104.17 | D12: Jan groceries/cafe (LIDL etc.)
B13: - Bank fees & charges | C13: -14.5 | D13: In-period commissions
B14: Computed closing balance | C14: =SUM(C5:C13) -> 35202.94
B15: Statement closing balance 25/06/2026 | C15: 35202.94
B16: Difference (ties to zero) | C16: =C14-C15 -> 0
B18: Cross-check - renovation funded from NBG
B19: Renovation from NBG per ledger | C19: ='Renovation Ledger'!E169 -> 106133.92
B20: Statement NBG renovation outflow (cash 64,730 + POS 4,494.92 + accountant 711) | C20: 69935.92
B21: Difference = cash float / timing (+ ~300 legal items the statement groups under acquisition) | C21: ='Renovation Ledger'!E169-69935.92 -> 36198
B23: The NBG account is fully reconciled to the official statement - there is NO unexplained money.
B24: The small ledger-vs-statement difference is cash float (cash withdrawn vs spent timing). ATM withdrawals are exact; renovation cash expenses are reconstructed weekly estimates.
B26: ROLLING BRIDGE — since last full statement (2026-06-25)
B27: Opening — statement closing balance (2026-06-25) | C27: 35202.94
B28: + Deposits since (dynamic — recalculates as new transfers are added) | C28: =SUMPRODUCT(('Funding (NBG Deposits)'!A5:A12>"2026-06-25")*('Funding (NBG Deposits)'!E5:E12="Yes")*'Funding (NBG Deposits)'!B5:B12) -> 50000
B29: - Renovation paid from NBG since (dynamic — recalculates as new expenses are added) | C29: =SUMPRODUCT(('Renovation Ledger'!I5:I166>"2026-06-25")*('Renovation Ledger'!H5:H166="Paid")*('Renovation Ledger'!G5:G166="Yes")*'Renovation Ledger'!E5:E166) -> 34610
B30: Computed balance (bridge) | C30: =C27+C28-C29 -> 50592.94
B31: Reported balance (2026-10-05) | C31: 49805
B32: Residual (bridge − reported) | C32: =C30-C31 -> 787.94
B33: A residual here is expected cash-float/timing (ATM withdrawals vs itemized weekly reconstructions), or spending not yet reported to Kobi -- see Flags & Dedup. It is NOT unexplained/missing money unless it grows unexpectedly large or keeps widening.

Sheet Flags & Dedup
A1: Flags & De-duplication Log
A2: Resolved items (green) and open questions (yellow). Nothing here is double-counted in the totals.
A4: # | B4: Issue | C4: How handled | D4: Status | E4: Action needed
A5: 1 | B5: Feb-8-2026 €20,000 transfer | C5: Confirmed in the Mizrahi euro-account statement (ref 30860) and project_data.js. Counted in deposits. | D5: Resolved | E5: None.
A6: 2 | B6: Hammer drill €380 (18-Jun) | C6: Confirmed SEPARATE from the €972.55 Athens shopping; added as its own line, charged to the Antonis contract. | D6: Resolved | E6: Recover the €380 by deducting it from the Antonis contract balance.
A7: 3 | B7: Vicky reimbursement €972.55 (Wise) | C7: A settlement of the €972.55 Athens expense; shown only on the Out-of-NBG tab, never double-counted. | D7: Resolved | E7: None - you confirmed it was sent.
A8: 4 | B8: May-28 cluster: excavator €600, plumber €1,000, electrician €1,000, plumber materials €300 | C8: All FOUR confirmed real (WhatsApp 28-May + dashboard) and added to the ledger. | D8: Resolved | E8: None.
A9: 5 | B9: Early items missing from Drive sheet: aluminium €1,150, plumber adv#1 €1,000, gate €50 | C9: Confirmed they belong; added to the ledger. | D9: Resolved | E9: None.
A10: 6 | B10: Acquisition detail and the €7,410 to Zoi | C10: Itemised from the Actual table: €7,410 is the property purchase TAX (FMA); balance split €107,000 (Zoe check) + €19,731 direct. | D10: Resolved | E10: None.
A11: 10 | B11: €2,000 transfer 31-May (ref 90833) | C11: Went to Wise as an unspent backup buffer; excluded from NBG deposits. | D11: Resolved | E11: None.
A12: 7 | B12: Reconciliation residual | C12: RESOLVED with the official NBG statement: the account reconciles to the cent (€35,202.94). The earlier residual was an expenses-vs-deposits artifact, not missing money. | D12: Resolved | E12: None.
A13: 8 | B13: Amanatidis + plumbing card payments (€2,140) | C13: RESOLVED per Kobi: paid with the NBG debit card; reclassified as From NBG = Yes. | D13: Resolved | E13: None.
A14: 9 | B14: Worker insurance Apr-Jun €3,858 | C14: Not present in the NBG statement -> confirms still UNPAID. Listed as Committed. | D14: OPEN | E14: Pay/confirm; then it moves to Paid.
A15: 11 | B15: EUR907.92 residual — rolling bridge (25-Jun to 11-Jul) | C15: Kobi reported the current NBG balance as EUR23,505.02 on 11-Jul-2026. The ledger only accounts for EUR10,790 in NBG-paid cash-out since the 25-Jun statement (EUR35,202.94), projecting EUR24,412.94 -- EUR907.92 more than reported. Consistent with the known cash-float pattern (round ATM withdrawals vs itemized weekly reconstructions) but could also be spending Vicky hasn't reported yet. | D15: OPEN | E15: Ask Vicky to confirm — either an ATM withdrawal that ran ahead of itemized expenses, or a payment not yet reported in the WhatsApp group.
... A17: 13 | B17: NBG balance EUR49,805 (Oct 5) + Kairis EUR400 gap | C17: Kobi reported EUR49,805 on 5-Oct = EUR58,805 (29-Jul) minus exactly three EUR3,000 ATM withdrawals (Sep 25, Sep 29, Oct 3). Sep 29 committed items (wages 950, steel 750, petrol 40, ELEC advance 250) + inferred Kairis 1,000 moved to Paid; Oct 3 report logged (wages 1,510, fuel 50, materials 150, ELEC 250, Kairis 1,050 = EUR3,010). Kairis: Sep 29 balance EUR4,400 minus logged EUR1,000 = EUR3,400, but Vicky Oct 3 says EUR3,000 -> EUR400 paid from somewhere unlogged (likely the Sep 25 EUR650 float). | D17: OPEN | E17: Ask Vicky: did EUR400 of the Sep 25 float go to Kairis? Confirm how the rest of the EUR650 float was spent. Rolling-bridge residual is the remaining cash-float timing gap.
